setup.cfg
setup.py
keras_elastic_callback/__init__.py
keras_elastic_callback.egg-info/PKG-INFO
keras_elastic_callback.egg-info/SOURCES.txt
keras_elastic_callback.egg-info/dependency_links.txt
keras_elastic_callback.egg-info/not-zip-safe
keras_elastic_callback.egg-info/requires.txt
keras_elastic_callback.egg-info/top_level.txt