Metadata-Version: 1.0
Name: keras-elastic-callback
Version: 0.1
Summary: Keras callbacks that sends all events and data to elasticsearch
Home-page: http://github.com/aocenas/keras_elastic_callback
Author: Andrej Ocenas
Author-email: mr.ocenas@gmail.com
License: MIT
Keywords: keras,elasticsearch,machine learning
Platform: UNKNOWN
